{
  "studentName": "Jacinta Piety",
  "studentID": "150118075",
  "studentSemester": 5,
  "studentAdvisor": "Doc. Dr. Murat Can GANIZ",
  "gpa": 2.8008474576271185,
  "dtoSchedule": [
    "               | Monday        | Tuesday       | Wednesday     | Thursday      | Friday        |",
    " 09:30 - 10:20 |               |               |               |               |               |",
    " 10:30 - 11:20 |               |               |               |               |               |",
    " 11:30 - 12:20 |               |               |               |               |               |",
    " 13:00 - 13:50 |               |               |               |               |               |",
    " 14:00 - 14:50 |               |               |               |               |               |",
    " 15:00 - 15:50 |               |               |               |               |               |",
    " 16:00 - 16:50 |               |               |               |               |               |",
    " 17:00 - 17:50 |               |               |               |               |               |"
  ],
  "actions": [],
  "studentTranscriptDto": {
    "letterGrades": [
      "ATA121:AA",
      "MBG1201:DD",
      "CSE1200:DC",
      "CSE1241:CB",
      "MATH1001:DC",
      "PHYS1101:CC",
      "PHYS1103:FD",
      "TRD121:CC",
      "ATA122:AA",
      "CSE1242:CC",
      "MATH1002:AA",
      "MATH2256:AA",
      "PHYS1102:AA",
      "PHYS1104:AA",
      "TRD122:FD",
      "BUS1003:AA",
      "CSE2023:CC",
      "CSE2225:CC",
      "ECON2004:DC",
      "EE2031:BA",
      "MATH2055:AA",
      "MATH2059:BB",
      "CSE2246:AA",
      "CSE2138:BB",
      "CSE2260:AA",
      "EE2032:BB",
      "STAT2253:AA"
    ]
  }
}