{
  "studentName": "Billie Biser",
  "studentID": "150118073",
  "studentSemester": 5,
  "studentAdvisor": "Doc. Dr. Borahan TUMER",
  "gpa": 2.4780701754385963,
  "dtoSchedule": [
    "               | Monday        | Tuesday       | Wednesday     | Thursday      | Friday        |",
    " 09:30 - 10:20 |               |        CSE3033|               |        CSE3215|               |",
    " 10:30 - 11:20 |        CSE3215|               |        CSE3063|               |               |",
    " 11:30 - 12:20 |        CSE3063|               |               |               |         TRD121|",
    " 13:00 - 13:50 |               |        CSE3033|               |               |        CSE3033|",
    " 14:00 - 14:50 |       PHYS1101|               |               |       PHYS1101|               |",
    " 15:00 - 15:50 |               |               |               |               |               |",
    " 16:00 - 16:50 |        CSE3215|        CSE3063|         TRD121|               |               |",
    " 17:00 - 17:50 |        CSE3033|               |               |        CSE3215|       PHYS1101|"
  ],
  "actions": [
    "[VERIFICATION-FAILED]:The advisor Doc. Dr. Borahan TUMER didnt approve the registration of the student150118073. Advisor didnt allow student to re-take DD or DC classes."
  ],
  "studentTranscriptDto": {
    "letterGrades": [
      "ATA121:CC",
      "MBG1201:CC",
      "CSE1200:AA",
      "CSE1241:CC",
      "MATH1001:FD",
      "PHYS1101:DC",
      "PHYS1103:BB",
      "TRD121:DC",
      "ATA122:DC",
      "CSE1242:CB",
      "MATH1002:DC",
      "MATH2256:BB",
      "PHYS1102:BB",
      "PHYS1104:AA",
      "TRD122:FF",
      "MGT1021:AA",
      "CSE2023:CC",
      "CSE2225:AA",
      "ECON2004:CC",
      "EE2031:CB",
      "MATH2055:CC",
      "CSE2246:CC",
      "CSE2138:AA",
      "CSE2260:CB",
      "EE2032:CB",
      "STAT2253:BA",
      "PHYS1101: ",
      "TRD121: ",
      "CSE3215: ",
      "CSE3033: ",
      "CSE3063: "
    ]
  }
}